JtocrTxAPI
