Metadata-Version: 2.1
Name: JtocrTxAPI
Version: 0.1.9
Summary: 截图OCR
Home-page: https://alidocs.dingtalk.com/i/p/4oJRz0VRJyvmLZMydy0mV7WvjQn7MG89
Author: ranxiaohang
Author-email: 17891967090@163.com
Classifier: Programming Language :: Python
Requires-Python: >=3.8
License-File: LICENSE.txt
